[
  {
    "element": "input",
    "type": "text",
    "name": "form-element-text-name",
    "htmlClass": "form-element-text-class",
    "id": "form-element-text-id",
    "value": "",
    "fieldIconClass": "icon-globe",
    "labelText": "Text input",
    "placeholder": "Placeholdertext",
    "required": false,
    "disabled": false,
    "scrollContainerForTooltip": ".page-wrapper"
  },
  {
    "component": "flexContainer",
    "formElements": [
      {
        "element": "input",
        "type": "text",
        "name": "form-element-username",
        "htmlClass": "form-element-text-class",
        "id": "form-element-username",
        "value": "default value",
        "fieldIconClass": "icon-user-profile",
        "labelText": "Username input",
        "placeholder": "Placeholdertext",
        "required": true,
        "disabled": false
      },
      {
        "element": "input",
        "type": "password",
        "name": "form-element-password-name",
        "htmlClass": "form-element-password-class",
        "id": "form-element-password-id",
        "value": "",
        "fieldIconClass": "icon-security-settings",
        "labelText": "Password input",
        "placeholder": "Placeholdertext",
        "required": false,
        "disabled": false
      }
    ]
  },
  {
    "element": "input",
    "type": "tel",
    "name": "form-element-tel-name",
    "htmlClass": "form-element-tel-class",
    "id": "form-element-tel-id",
    "value": "default value",
    "fieldIconClass": "icon-phone",
    "labelText": "Telephone input (disabled)",
    "placeholder": "Placeholdertext",
    "required": false,
    "disabled": true
  },
  {
    "element": "input",
    "type": "email",
    "name": "form-element-email-name",
    "htmlClass": "form-element-email-class",
    "id": "form-element-email-id",
    "value": "default value",
    "fieldIconClass": "icon-mail",
    "labelText": "Email input (with icon)",
    "placeholder": "Placeholdertext",
    "required": false,
    "disabled": false
  },
  {
    "element": "select",
    "name": "form-element-select-name",
    "htmlClass": "form-element-select-class",
    "id": "form-element-select-id",
    "value": "option2",
    "selectOptions": [
      {
        "text": "Please select...",
        "value": ""
      },
      {
        "text": "Option 1",
        "value": "option1"
      },
      {
        "text": "Option 2",
        "value": "option2"
      },
      {
        "text": "Option 3",
        "value": "option3"
      }
    ],
    "labelText": "Select",
    "required": false,
    "disabled": false
  },
  {
    "element": "input",
    "type": "checkbox",
    "name": "form-element-checkbox-name",
    "htmlClass": "form-element-checkbox-class",
    "id": "form-element-checkbox-id1",
    "value": "checkboxInputValue1",
    "inputValue": "checkboxInputValue1",
    "labelText": "Checkbox",
    "required": false,
    "disabled": false
  },
  {
    "element": "input",
    "type": "checkbox",
    "name": "form-element-checkbox-name",
    "htmlClass": "form-element-checkbox-class",
    "id": "form-element-checkbox-id2",
    "inputValue": "checkboxInputValue2",
    "labelText": "Checkbox",
    "required": false,
    "disabled": false
  },
  {
    "element": "input",
    "type": "radio",
    "name": "form-element-radio-name",
    "htmlClass": "form-element-radio-class",
    "id": "form-element-radio-id1",
    "inputValue": "valueRadioButton1",
    "labelText": "Radio",
    "required": false,
    "disabled": false
  },
  {
    "element": "input",
    "type": "radio",
    "name": "form-element-radio-name",
    "htmlClass": "form-element-radio-class",
    "id": "form-element-radio-id2",
    "value": "valueRadioButton2",
    "inputValue": "valueRadioButton2",
    "labelText": "Radio",
    "required": false,
    "disabled": false
  },
  {
    "element": "textarea",
    "name": "form-element-textarea-name",
    "htmlClass": "form-element-textarea-class",
    "id": "form-element-textarea-id",
    "value": "default value",
    "labelText": "Textarea",
    "placeholder": "Placeholdertext",
    "required": false,
    "disabled": false,
    "maxlength": 500
  },
  {
    "component": "flexContainer",
    "formElements": [
      {
        "component": "CmdInputGroup",
        "labelText": "Input Group (Checkbox):",
        "toggleSwitches": true,
        "inputTypes": "checkbox",
        "value": ["checkbox-website"],
        "name": "input-group-checkboxes",
        "inputElements": [
          {
            "labelText": "Website",
            "id": "checkbox-id-1",
            "name": "input-group-checkbox",
            "iconClass": "icon-globe",
            "value": "checkbox-website"
          },
          {
            "labelText": "E-Mail",
            "id": "checkbox-id-2",
            "name": "input-group-checkbox",
            "iconClass": "icon-mail",
            "value": "checkbox-email"
          },
          {
            "labelText": "Phone",
            "id": "checkbox-id-3",
            "name": "input-group-checkbox",
            "iconClass": "icon-phone",
            "value": "checkbox-phone"
          }
        ]
      },
      {
        "component": "CmdInputGroup",
        "labelText": "Input Group (Radio):",
        "toggleSwitches": true,
        "value": "radio-website",
        "name": "input-group-radiobuttons",
        "inputElements": [
          {
            "labelText": "Website",
            "id": "radio-id-1",
            "name": "input-group-radio",
            "iconClass": "icon-globe",
            "value": "radio-website"
          },
          {
            "labelText": "E-Mail",
            "id": "radio-id-2",
            "name": "input-group-radio",
            "iconClass": "icon-mail",
            "value": "radio-email"
          },
          {
            "labelText": "Phone",
            "id": "radio-id-3",
            "name": "input-group-radio",
            "iconClass": "icon-phone",
            "value": "radio-phone"
          }
        ]
      }
    ]
  }
]